{"mc":{"body":{"frameRate":8,"frames":[{"res":"0000000.png","x":-56,"y":-56},{"res":"0000001.png","x":-62,"y":-63},{"res":"0000002.png","x":-61,"y":-64},{"res":"0000003.png","x":-63,"y":-64},{"res":"0000004.png","x":-63,"y":-64},{"res":"0000005.png","x":-63,"y":-64},{"res":"0000006.png","x":-59,"y":-60},{"res":"0000007.png","x":-58,"y":-60},{"res":"0000008.png","x":-58,"y":-55},{"res":"0000009.png","x":-58,"y":-52}]}},"res":{"0000000.png":{"x":119,"y":128,"w":113,"h":108},"0000001.png":{"x":256,"y":0,"w":126,"h":125},"0000002.png":{"x":129,"y":0,"w":125,"h":126},"0000003.png":{"x":0,"y":0,"w":127,"h":126},"0000004.png":{"x":384,"y":0,"w":125,"h":122},"0000005.png":{"x":384,"y":124,"w":123,"h":120},"0000006.png":{"x":256,"y":127,"w":119,"h":115},"0000007.png":{"x":0,"y":128,"w":117,"h":116},"0000008.png":{"x":119,"y":238,"w":108,"h":110},"0000009.png":{"x":229,"y":244,"w":107,"h":104}}}