{"frameRate":30,"name":"150302031","version":"5.5","compatibleVersion":"5.5","armature":[{"type":"Armature","frameRate":30,"name":"150302031","aabb":{"x":-28.99,"y":-31.48,"width":50,"height":46},"bone":[{"name":"root"},{"name":"eye","parent":"root"},{"length":9,"name":"eye2","parent":"eye","transform":{"x":-1.21,"y":3.16,"skX":-91.36,"skY":-91.36}}],"slot":[{"name":"eye","parent":"eye2"}],"skin":[{"slot":[{"name":"eye","display":[{"name":"eye","transform":{"x":11.7,"y":-2.5,"skX":92.88,"skY":92.88}},{"name":"eye_3","transform":{"x":10.41,"y":-4.13,"skX":91.36,"skY":91.36}},{"name":"eye_5","transform":{"x":9.63,"y":-3.63,"skX":91.36,"skY":91.36}}]}]}],"animation":[{"duration":32,"name":"dead","bone":[{"name":"eye2","translateFrame":[{"duration":2,"tweenEasing":0},{"duration":13,"tweenEasing":0,"x":-0.69,"y":1.1},{"duration":9,"tweenEasing":0,"x":1.03,"y":-0.31},{"duration":8,"tweenEasing":0,"x":-0.91,"y":-2.96},{"duration":0,"x":-1.24,"y":-2.92}]}],"slot":[{"name":"eye","displayFrame":[{"duration":2},{"duration":30,"value":1}]}]},{"duration":0,"name":"fight"},{"duration":10,"name":"hit","bone":[{"name":"eye2","translateFrame":[{"duration":3,"tweenEasing":0},{"duration":7,"tweenEasing":0,"x":-1.53,"y":-1.25},{"duration":0,"x":0.77,"y":-0.3}]}],"slot":[{"name":"eye","displayFrame":[{"duration":3},{"duration":7,"value":2},{"duration":0}],"colorFrame":[{"duration":3,"curve":[0.142,0,0.8125,0.69]},{"duration":2,"curve":[0.1555,0.13,0.8255,0.8049999999999999],"value":{"rM":33,"gM":31,"bM":31}},{"duration":3,"curve":[0.33,0.32,0.67,0.68]},{"duration":2,"curve":[0.349,0.39,0.689,0.74],"value":{"rM":25,"gM":24,"bM":24}},{"duration":0}]}]},{"duration":0,"name":"jump","bone":[{"name":"eye2","translateFrame":[{"duration":0,"x":-1.51,"y":1.8}]}]},{"duration":37,"name":"skill1","bone":[{"name":"eye2","translateFrame":[{"duration":4,"tweenEasing":0},{"duration":33,"tweenEasing":0,"x":-1.43,"y":-1.7},{"duration":0}]}],"slot":[{"name":"eye","displayFrame":[{"duration":27},{"duration":7,"value":1},{"duration":3}]}]},{"duration":40,"name":"skill2","bone":[{"name":"eye2","translateFrame":[{"duration":4,"tweenEasing":0},{"duration":36,"tweenEasing":0,"x":-1.22,"y":-1.14},{"duration":0}]}]},{"duration":30,"name":"skill3","bone":[{"name":"eye2","translateFrame":[{"duration":3,"tweenEasing":0},{"duration":27,"tweenEasing":0,"x":-0.77,"y":-0.47},{"duration":0}]}]},{"duration":25,"name":"skill4","bone":[{"name":"eye2","translateFrame":[{"duration":4,"tweenEasing":0},{"duration":4,"tweenEasing":0,"x":-1.4,"y":-1.44},{"duration":17,"tweenEasing":0,"x":-0.11,"y":0.7},{"duration":0}]}]},{"duration":40,"name":"stand","bone":[{"name":"eye2","translateFrame":[{"duration":19,"tweenEasing":0},{"duration":21,"tweenEasing":0,"x":-0.2,"y":-1.2},{"duration":0}]}],"slot":[{"name":"eye","displayFrame":[{"duration":13},{"duration":7,"value":1},{"duration":20}]}]},{"duration":0,"name":"walk"}],"defaultActions":[{"gotoAndPlay":"dead"}]}]}