{"mc":{"body":{"frameRate":12,"frames":[{"res":"000000.png","x":-98,"y":-228},{"res":"000001.png","x":-88,"y":-280},{"res":"000002.png","x":-84,"y":-325},{"res":"000003.png","x":-114,"y":-318},{"res":"000004.png","x":-114,"y":-306},{"res":"000005.png","x":-114,"y":-305},{"res":"000006.png","x":-114,"y":-298},{"res":"000007.png","x":-114,"y":-293},{"res":"000008.png","x":-114,"y":-293},{"res":"000009.png","x":-36,"y":-24}]}},"res":{"000000.png":{"x":1659,"y":343,"w":264,"h":294},"000001.png":{"x":1659,"y":0,"w":356,"h":341},"000002.png":{"x":423,"y":0,"w":390,"h":387},"000003.png":{"x":0,"y":0,"w":421,"h":377},"000004.png":{"x":815,"y":0,"w":420,"h":352},"000005.png":{"x":1237,"y":0,"w":420,"h":350},"000006.png":{"x":1237,"y":352,"w":419,"h":340},"000007.png":{"x":815,"y":354,"w":419,"h":335},"000008.png":{"x":0,"y":379,"w":419,"h":335},"000009.png":{"x":421,"y":389,"w":252,"h":52}}}